getdominantcolor/README.MD
getdominantcolor/__init__.py
getdominantcolor/requirements.txt
getdominantcolor/thirdparty.json
getdominantcolor-0.10.dist-info/LICENSE.rst
getdominantcolor-0.10.dist-info/METADATA
getdominantcolor-0.10.dist-info/WHEEL
getdominantcolor-0.10.dist-info/top_level.txt
getdominantcolor-0.10.dist-info/RECORD
