Metadata-Version: 2.1
Name: getdominantcolor
Version: 0.10
Summary: Extracts the dominant color from an image represented by an array.
Home-page: https://github.com/hansalemaos/getdominantcolor
Author: Johannes Fischer
Author-email: aulasparticularesdealemaosp@gmail.com
License: MIT
Keywords: rgb,find
Classifier: Development Status :: 4 - Beta
Classifier: Programming Language :: Python :: 3 :: Only
Classifier: Programming Language :: Python :: 3.10
Classifier: Topic :: Software Development :: Libraries :: Python Modules
Classifier: Topic :: Utilities
License-File: LICENSE.rst
Requires-Dist: numexpr
Requires-Dist: numpy
